grokhelper/__init__.py
grokhelper/core.py
grokhelper-0.1.3.dist-info/METADATA
grokhelper-0.1.3.dist-info/WHEEL
grokhelper-0.1.3.dist-info/top_level.txt
grokhelper-0.1.3.dist-info/RECORD
